nonebot_plugin_group_file_admin/__init__.py
nonebot_plugin_group_file_admin/config.py
nonebot_plugin_group_file_admin/dataclass.py
nonebot_plugin_group_file_admin/model.py
nonebot_plugin_group_file_admin-0.1.3.dist-info/METADATA
nonebot_plugin_group_file_admin-0.1.3.dist-info/WHEEL
nonebot_plugin_group_file_admin-0.1.3.dist-info/top_level.txt
nonebot_plugin_group_file_admin-0.1.3.dist-info/RECORD
