Metadata-Version: 2.2
Name: nonebot-plugin-group-file-admin
Version: 0.1.3
Summary: Default template for PDM package
Author-email: zhongwen-4 <2401128923@qq.com>
License: MIT
Requires-Python: >=3.10
Requires-Dist: nonebot-plugin-localstore>=0.7.3
Requires-Dist: nonebot-plugin-waiter>=0.8.1
Requires-Dist: httpx>=0.28.1
Requires-Dist: nonebot2>=2.4.1
Requires-Dist: nonebot-adapter-onebot>=2.4.6
